Metadata-Version: 2.1
Name: xubib
Version: 1.0.7
Summary: this is my first test
Home-page: https://gitee.com/chen-kun19/summer-program
Author: xushibo
Author-email: 937207118@qq.com
License: MIT
Platform: UNKNOWN
